discordbot/__init__.py
discordbot/colors.py
discordbot/discordbot.py
discordbot/embeds.py
discordbot/messages.py
discordbot/utilities.py
discordbot/bot_utils/__init__.py
discordbot/bot_utils/checks.py
discordbot/bot_utils/config.py
discordbot/bot_utils/formats.py
discordbot/bot_utils/paginator.py
discordbot/cogs/__init__.py
discordbot/cogs/botadmin.py
discordbot/cogs/meta.py
discordbot/cogs/reactions.py
discordbot.py-0.2.3a3.dist-info/DESCRIPTION.rst
discordbot.py-0.2.3a3.dist-info/METADATA
discordbot.py-0.2.3a3.dist-info/RECORD
discordbot.py-0.2.3a3.dist-info/WHEEL
discordbot.py-0.2.3a3.dist-info/metadata.json
discordbot.py-0.2.3a3.dist-info/top_level.txt
