Metadata-Version: 1.2
Name: discordbot.py
Version: 0.2.3a3
Summary: A wrapper for discord.py with advanced functionality
Home-page: https://github.com/rauenzi/discordbot.py
Author: Zack Rauen
Author-email: rauenzi@outlook.com
License: MIT
Keywords: discord framework development
Platform: UNKNOWN
Classifier: Development Status :: 3 - Alpha
Classifier: Intended Audience :: Developers
Classifier: Natural Language :: English
Classifier: Operating System :: OS Independent
Classifier: Topic :: Software Development :: Build Tools
Classifier: License :: OSI Approved :: MIT License
Classifier: Programming Language :: Python :: 3.5
Classifier: Programming Language :: Python :: 3.6
Classifier: Topic :: Internet
Classifier: Topic :: Software Development :: Libraries
Classifier: Topic :: Software Development :: Libraries :: Python Modules
Classifier: Topic :: Utilities
Requires-Python: >=3.5
